[
    {
        "name": "真不敢相信",
        "file_name": "真不敢相信.jpg",
        "description": "真不敢相信"
    },
    {
        "name": "我也一樣",
        "file_name": "我也一樣.jpg",
        "description": "我也一樣"
    },
    {
        "name": "因為我很想要嘛",
        "file_name": "因為我很想要嘛.jpg",
        "description": "出自第11集，愛音和團員去看效果器時表示很想要",
        "tags": ["愛音"],
        "author": "愛音",
        "episode": 11
    },
    {
        "name": "每次想著想著就會感到很厭世",
        "file_name": "每次想著想著就會感到很厭世.jpg",
        "description": "每次想著想著就會感到很厭世"
    },
    {
        "name": "妳誤會了",
        "file_name": "妳誤會了.jpg",
        "description": "出自第8集，爽世和祥子談判時的否認",
        "tags": ["爽世"],
        "author": "爽世",
        "episode": 8
    },
    {
        "name": "我想應該不是",
        "file_name": "我想應該不是.jpg",
        "description": "我想應該不是"
    },
    {
        "name": "這算什麼",
        "file_name": "這算什麼.jpg",
        "description": "這算什麼"
    },
    {
        "name": "真是太對了",
        "file_name": "真是太對了.jpg",
        "description": "真是太對了"
    },
    {
        "name": "妳不僅表裡不一，又滿口謊言",
        "file_name": "妳不僅表裡不一，又滿口謊言.jpg",
        "description": "妳不僅表裡不一，又滿口謊言"
    },
    {
        "name": "差勁",
        "file_name": "差勁.jpg",
        "description": "差勁"
    },
    {
        "name": "也沒有啦",
        "file_name": "也沒有啦.jpg",
        "description": "出自第5集，愛音在回憶中被同學稱讚時的回應",
        "tags": ["愛音"],
        "author": "愛音",
        "episode": 5
    },
    {
        "name": "妳是來找我吵架的嗎",
        "file_name": "妳是來找我吵架的嗎.jpg",
        "description": "妳是來找我吵架的嗎"
    },
    {
        "name": "我沒有那麼厲害啦",
        "file_name": "我沒有那麼厲害啦.jpg",
        "description": "我沒有那麼厲害啦"
    },
    {
        "name": "妳在開玩笑嗎",
        "file_name": "妳在開玩笑嗎.jpg",
        "description": "出自第4集，愛音對於樂團亂出主意時，立希的質疑",
        "tags": ["立希","愛音"],
        "author": "立希",
        "episode": 4
    },
    {
        "name": "為什麼不行",
        "file_name": "為什麼不行.jpg",
        "description": "為什麼不行"
    },
    {
        "name": "是沒錯啊",
        "file_name": "是沒錯啊.jpg",
        "description": "是沒錯啊"
    },
    {
        "name": "又來了一個新人",
        "file_name": "又來了一個新人.jpg",
        "description": "出自第13集，ave_mujica初次公演時的劇情",
        "tags": ["mujica", "喵夢", "若麥"],
        "author": "喵夢",
        "episode": 13
    },
    {
        "name": "是一輩子喔 一輩子",
        "file_name": "是一輩子喔_一輩子.jpg",
        "description": "是一輩子喔 一輩子"
    },
    {
        "name": "我懂",
        "file_name": "我懂.jpg",
        "description": "我懂"
    },
    {
        "name": "不要逃啦",
        "file_name": "不要逃啦.jpg",
        "description": "出自第6集，立希躲在學校逃避被愛音和燈堵門時愛音說的話",
        "tags": ["立希", "愛音"],
        "author": "愛音",
        "episode": 6
    },
    {
        "name": "謝謝妳",
        "file_name": "謝謝妳.jpg",
        "description": "謝謝妳"
    },
    {
        "name": "這個不用了",
        "file_name": "這個不用了.jpg",
        "description": "這個不用了"
    },
    {
        "name": "好可愛喔",
        "file_name": "好可愛喔.jpg",
        "description": "好可愛喔"
    },
    {
        "name": "這傢伙根本什麼也不懂",
        "file_name": "這傢伙根本什麼也不懂.jpg",
        "description": "這傢伙根本什麼也不懂"
    },
    {
        "name": "讓我們一起迷失吧",
        "file_name": "讓我們一起迷失吧.jpg",
        "description": "讓我們一起迷失吧"
    },
    {
        "name": "那真是可喜可賀",
        "file_name": "那真是可喜可賀.jpg",
        "description": "那真是可喜可賀"
    },
    {
        "name": "一輩子跟我一起組樂團嗎",
        "file_name": "一輩子跟我一起組樂團嗎.jpg",
        "description": "出自第1集，燈在KTV中對愛音說出的話",
        "tags": ["燈", "一輩子", "第1集"],
        "author": "燈",
        "episode": 9
    },
    {
        "name": "原來妳是這麼想的呀",
        "file_name": "原來妳是這麼想的呀.jpg",
        "description": "出自第4集，舊團員溝通時爽世假意敷衍燈的台詞",
        "tags": ["爽世"],
        "author": "爽世",
        "episode": 4
    },
    {
        "name": "為什麼都不回答我啊",
        "file_name": "為什麼都不回答我啊.jpg",
        "description": "為什麼都不回答我啊"
    },
    {
        "name": "我有啊",
        "file_name": "我有啊.jpg",
        "description": "我有啊"
    },
    {
        "name": "我不會再演奏春日影了",
        "file_name": "我不會再演奏春日影了.jpg",
        "description": "我不會再演奏春日影了"
    },
    {
        "name": "妳到底是怎樣啊",
        "file_name": "妳到底是怎樣啊.jpg",
        "description": "妳到底是怎樣啊"
    },
    {
        "name": "愛音驚訝",
        "file_name": "愛音驚訝.jpg",
        "description": "愛音驚訝"
    },
    {
        "name": "愛音:蛤",
        "file_name": "愛音_蛤.jpg",
        "description": "愛音:蛤"
    },
    {
        "name": "好厲害",
        "file_name": "好厲害.jpg",
        "description": "好厲害"
    },
    {
        "name": "怎麼會...簡直不敢相信",
        "file_name": "怎麼會...簡直不敢相信.jpg",
        "description": "怎麼會...簡直不敢相信"
    },
    {
        "name": "立希看手機",
        "file_name": "立希看手機.jpg",
        "description": "立希看手機"
    },
    {
        "name": "滿腦子都只想到自己呢",
        "file_name": "滿腦子都只想到自己呢.jpg",
        "description": "滿腦子都只想到自己呢"
    },
    {
        "name": "來，開始溝通吧",
        "file_name": "來，開始溝通吧.jpg",
        "description": "出自第4集，愛音把舊Crichic成員全部拖出來叫他們好好溝通",
        "tags": ["愛音"],
        "author": "愛音",
        "episode": 4
    },
    {
        "name": "我考慮一下吧",
        "file_name": "我考慮一下吧.jpg",
        "description": "我考慮一下吧"
    },
    {
        "name": "是嗎",
        "file_name": "是嗎.jpg",
        "description": "是嗎"
    },
    {
        "name": "我願意一輩子和燈在一起",
        "file_name": "我願意一輩子和燈在一起.jpg",
        "description": "我願意一輩子和燈在一起"
    },
    {
        "name": "不錯吧",
        "file_name": "不錯吧.jpg",
        "description": "出自第12集，愛音在表演完將團名確定為MyGO!!!!!",
        "tags": ["愛音", "Crichic"],
        "author": "愛音",
        "episode": 12
    },
    {
        "name": "爽世大小眼",
        "file_name": "爽世大小眼.jpg",
        "description": "爽世大小眼"
    },
    {
        "name": "我都說了討厭了吧",
        "file_name": "我都說了討厭了吧.jpg",
        "description": "我都說了討厭了吧"
    },
    {
        "name": "只要是我能做的，我什麼都願意做",
        "file_name": "只要是我能做的，我什麼都願意做.jpg",
        "description": "出自第8集，爽世跪地的名場面(學狗叫，三回啊三回)",
        "tags": ["爽世", "祥子"],
        "author": "爽世",
        "episode": 8
    },
    {
        "name": "我都會全力以赴的",
        "file_name": "我都會全力以赴的.jpg",
        "description": "我都會全力以赴的"
    },
    {
        "name": "妳要不要先去洗澡",
        "file_name": "妳要不要先去洗澡.jpg",
        "description": "妳要不要先去洗澡"
    },
    {
        "name": "爽世：別這樣啦",
        "file_name": "別這樣啦2.jpg",
        "description": "出自第11集，爽世和愛音講開之後叫爽世soyorin，爽世：別這樣啦",
        "tags": ["爽世", "愛音"],
        "author": "爽世",
        "episode": 11
    },
    {
        "name": "祥子：是這樣嗎",
        "file_name": "是這樣嗎.jpg",
        "description": "祥子：是這樣嗎"
    },
    {
        "name": "這是在報復我嗎",
        "file_name": "這是在報復我嗎.jpg",
        "description": "這是在報復我嗎"
    },
    {
        "name": "那...那我呢",
        "file_name": "那...那我呢.jpg",
        "description": "那...那我呢"
    },
    {
        "name": "抱歉",
        "file_name": "抱歉.jpg",
        "description": "抱歉"
    },
    {
        "name": "聽起來好棒喔",
        "file_name": "聽起來好棒喔.jpg",
        "description": "聽起來好棒喔"
    },
    {
        "name": "我不參加",
        "file_name": "我不參加.jpg",
        "description": "我不參加"
    },
    {
        "name": "我完全不懂妳的意思",
        "file_name": "我完全不懂妳的意思.jpg",
        "description": "我完全不懂妳的意思"
    },
    {
        "name": "就由我來將它結束掉",
        "file_name": "就由我來將它結束掉.jpg",
        "description": "就由我來將它結束掉"
    },
    {
        "name": "為什麼要演奏春日影",
        "file_name": "為什麼要演奏春日影.jpg",
        "description": "為什麼要演奏春日影"
    },
    {
        "name": "什麼意思",
        "file_name": "什麼意思.jpg",
        "description": "出自第10集，愛音到爽世家直球對決時，爽世的質疑",
        "tags": ["爽世","愛音"],
        "author": "爽世",
        "episode": 10
    },
    {
        "name": "我沒說過那種話",
        "file_name": "我沒說過那種話.jpg",
        "description": "我沒說過那種話"
    },
    {
        "name": "不讓我們看看我們怎麼知道",
        "file_name": "不讓我們看看怎麼知道.jpg",
        "description": "出自第3集，祥子表示燈有作詞時，其他人的反應，這句話出自立希之口",
        "tags": ["立希", "Crichic"],
        "author": "立希",
        "episode": 3
    },
    {
        "name": "我愛慕虛榮啦",
        "file_name": "我愛慕虛榮啦.jpg",
        "description": "我愛慕虛榮啦"
    },
    {
        "name": "不行",
        "file_name": "不行.jpg",
        "description": "出自第3集，Crichic去唱KTV時爽世說的話",
        "tags": ["爽世", "Crichic"],
        "author": "爽世",
        "episode": 3
    },
    {
        "name": "真的嗎",
        "file_name": "真的嗎.jpg",
        "description": "真的嗎"
    },
    {
        "name": "謝謝妳",
        "file_name": "謝謝妳.jpg",
        "description": "謝謝妳"
    },
    {
        "name": "味道醇香，我很喜歡",
        "file_name": "味道純香，我很喜歡.jpg",
        "description": "出自第2集，愛音和爽世問推薦的飲料，爽世對紅茶的評價",
        "tags": ["爽世", "愛音"],
        "author": "爽世",
        "episode": 2
    },
    {
        "name": "感謝您讓我佔用的寶貴時間",
        "file_name": "感謝您讓我佔用的寶貴時間.jpg",
        "description": "感謝您讓我佔用的寶貴時間"
    },
    {
        "name": "太過分了",
        "file_name": "太過分了.jpg",
        "description": "出自第8集，在春日影演奏之後的爽世的崩潰",
        "tags": ["爽世"],
        "author": "爽世",
        "episode": 8
    },
    {
        "name": "我都說一直有在看了啊",
        "file_name": "我都說一直有在看了啊.jpg",
        "description": "我都說一直有在看了啊"
    },
    {
        "name": "這樣啊",
        "file_name": "這樣啊.jpg",
        "description": "這樣啊"
    },
    {
        "name": "喵夢：別這樣啦",
        "file_name": "別這樣啦.jpg",
        "description": "出自第13集，喵夢跑去偷拍舞台被抓包，手機被祥子沒收的抗拒",
        "tags": ["喵夢","若麥"],
        "author": "喵夢",
        "episode": 13
    },
    {
        "name": "真的很莫名其妙",
        "file_name": "真的很莫名其妙.jpg",
        "description": "真的很莫名其妙"
    },
    {
        "name": "交給我吧",
        "file_name": "交給我吧.jpg",
        "description": "出自第1集，睦拒絕和爽世去找祥子之後爽世說的話",
        "tags": ["爽世"],
        "author": "爽世",
        "episode": 1
    },
    {
        "name": "她是我朋友",
        "file_name": "她是我朋友.jpg",
        "description": "她是我朋友"
    },
    {
        "name": "我的人生已經失敗了吧",
        "file_name": "我的人生已經失敗了吧.jpg",
        "description": "我的人生已經失敗了吧"
    },
    {
        "name": "因為春日影是一首好歌",
        "file_name": "因為春日影是一首好歌.jpg",
        "description": "出自第4集，開頭愛音對燈所說的鼓勵話語",
        "tags": ["愛音", "燈"],
        "author": "愛音",
        "episode": 4
    },
    {
        "name": "真的毫無品味",
        "file_name": "真的毫無品味.jpg",
        "description": "真的毫無品味"
    },
    {
        "name": "好厲害...",
        "file_name": "好厲害....jpg",
        "description": "好厲害..."
    },
    {
        "name": "愛音模糊",
        "file_name": "愛音模糊.jpg",
        "description": "愛音模糊"
    },
    {
        "name": "不是這樣的",
        "file_name": "不是這樣的.jpg",
        "description": "出自第8集，爽世試探祥子有沒有考慮的意願，睦的否認",
        "tags": ["爽世", "睦"],
        "author": "睦",
        "episode": 8
    },
    {
        "name": "好硬派",
        "file_name": "好硬派.jpg",
        "description": "好硬派"
    },
    {
        "name": "我已經搞不懂了",
        "file_name": "我已經搞不懂了.jpg",
        "description": "我已經搞不懂了"
    },
    {
        "name": "不爽世",
        "file_name": "不爽世.jpg",
        "description": "出自第11集，不爽世對愛音決定要做衣服卻拖其他人一起幫忙感到不耐煩",
        "tags": ["爽世"],
        "author": "爽世",
        "episode": 11
    },
    {
        "name": "真的是很不容易呢",
        "file_name": "真的是很不容易呢.jpg",
        "description": "真的是很不容易呢"
    },
    {
        "name": "找不到耶",
        "file_name": "找不到耶.jpg",
        "description": "找不到耶"
    },
    {
        "name": "妳怎麼會這麼想",
        "file_name": "妳怎麼會這麼想.jpg",
        "description": "妳怎麼會這麼想"
    },
    {
        "name": "是又怎樣",
        "file_name": "是又怎樣.jpg",
        "description": "是又怎樣"
    },
    {
        "name": "所以我才受不了大人",
        "file_name": "所以我才受不了大人.jpg",
        "description": "所以我才受不了大人"
    },
    {
        "name": "能否請妳積極考慮我的提案呢",
        "file_name": "能否請妳積極考慮我的提案呢.jpg",
        "description": "能否請妳積極考慮我的提案呢"
    },
    {
        "name": "我要",
        "file_name": "我要.jpg",
        "description": "我要"
    },
    {
        "name": "在這裡想叫都沒問題",
        "file_name": "在這裡想叫都沒問題.jpg",
        "description": "出自第3集，祥子在天橋上大喊",
        "tags": ["祥子", "燈"],
        "author": "祥子",
        "episode": 3
    },
    {
        "name": "不要講這種話",
        "file_name": "不要講這種話.jpg",
        "description": "出自第6集，立希要其他人不要抱怨",
        "tags": ["立希"],
        "author": "立希",
        "episode": 6
    },
    {
        "name": "沒有人那樣拜託妳",
        "file_name": "沒有人那樣拜託妳.jpg",
        "description": "沒有人那樣拜託妳"
    },
    {
        "name": "現在沒時間玩了吧",
        "file_name": "現在沒時間玩了吧.jpg",
        "description": "現在沒時間玩了吧"
    },
    {
        "name": "立希：蛤",
        "file_name": "立希_蛤.jpg",
        "description": "立希：蛤"
    },
    {
        "name": "這樣很沒有教養喔",
        "file_name": "這樣很沒有教養喔.jpg",
        "description": "這樣很沒有教養喔"
    },
    {
        "name": "睦：是這樣嗎",
        "file_name": "是這樣嗎2.jpg",
        "description": "睦：是這樣嗎"
    },
    {
        "name": "愛音泡澡",
        "file_name": "愛音泡澡.jpg",
        "description": "愛音泡澡"
    },
    {
        "name": "我亂說的",
        "file_name": "我亂說的.jpg",
        "description": "我亂說的"
    },
    {
        "name": "愛音：我不知道",
        "file_name": "我不知道2.jpg",
        "description": "愛音：我不知道"
    },
    {
        "name": "天啊，大發現欸",
        "file_name": "天啊，大發現欸.jpg",
        "description": "出自第12集，愛音登台前對爛雙關感到意外",
        "tags": ["愛音"],
        "author": "愛音",
        "episode": 12
    },
    {
        "name": "不是很可愛嗎",
        "file_name": "不是很可愛嗎.jpg",
        "description": "出自第11集，在爽世家時愛音對爽世表示soyorin這個暱稱很可愛",
        "tags": ["愛音", "第11集"],
        "author": "愛音",
        "episode": 11
    },
    {
        "name": "妳想幹嘛",
        "file_name": "妳想幹嘛.jpg",
        "description": "妳想幹嘛"
    },
    {
        "name": "為什麼都不講話",
        "file_name": "為什麼都不講話.jpg",
        "description": "為什麼都不講話"
    },
    {
        "name": "樂奈抹茶巴菲",
        "file_name": "樂奈抹茶巴菲.jpg",
        "description": "樂奈抹茶巴菲"
    },
    {
        "name": "祥子驚嚇",
        "file_name": "祥子驚嚇.jpg",
        "description": "祥子驚嚇"
    },
    {
        "name": "是這樣沒錯",
        "file_name": "是這樣沒錯.jpg",
        "description": "是這樣沒錯"
    },
    {
        "name": "這是在講什麼",
        "file_name": "這是在講什麼.jpg",
        "description": "這是在講什麼"
    },
    {
        "name": "妳想說什麼",
        "file_name": "妳想說什麼.jpg",
        "description": "妳想說什麼"
    },
    {
        "name": "這...",
        "file_name": "這....jpg",
        "description": "這..."
    },
    {
        "name": "我早知道會這樣了",
        "file_name": "我早知道會這樣了.jpg",
        "description": "我早知道會這樣了"
    },
    {
        "name": "我好難受...好難受...",
        "file_name": "我好難受...好難受....jpg",
        "description": "我好難受...好難受..."
    },
    {
        "name": "來",
        "file_name": "來.jpg",
        "description": "出自第6集，樂奈交出手機給mygo成員加好友",
        "tags": ["樂奈", "貓貓"],
        "author": "樂奈",
        "episode": 6
    },
    {
        "name": "我看妳只是在逃避吧",
        "file_name": "我看妳只是在逃避吧.jpg",
        "description": "我看妳只是在逃避吧"
    },
    {
        "name": "太先入為主了喔",
        "file_name": "太先入為主了喔.jpg",
        "description": "出自第4集，愛音對於立希駁回想法的反應",
        "tags": ["愛音", "立希"],
        "author": "愛音",
        "episode": 4
    },
    {
        "name": "妳先再稍微等一下吧",
        "file_name": "妳先再稍微等一下吧.jpg",
        "description": "妳先再稍微等一下吧"
    },
    {
        "name": "坦白說我都聽得一頭霧水",
        "file_name": "坦白說我都聽得一頭霧水.jpg",
        "description": "出自第13集，爽世和燈在天橋上的對話",
        "tags": ["爽世", "燈"],
        "author": "爽世",
        "episode": 13
    },
    {
        "name": "它沒有結束",
        "file_name": "它沒有結束.jpg",
        "description": "它沒有結束"
    },
    {
        "name": "對不起，忍不住就",
        "file_name": "對不起，忍不住就.jpg",
        "description": "對不起，忍不住就"
    },
    {
        "name": "事情都搞砸了",
        "file_name": "事情都搞砸了.jpg",
        "description": "出自第2集，睦跑到羽丘找祥子，讓祥子覺得事情差點砸了",
        "tags": ["睦", "祥子"],
        "author": "祥子",
        "episode": 2
    },
    {
        "name": "我想妳心裡多少也有些想法吧",
        "file_name": "我想妳心裡多少也有些想法吧.jpg",
        "description": "我想妳心裡多少也有些想法吧"
    },
    {
        "name": "還有這樣太不負責了吧",
        "file_name": "還有這樣太不負責了吧.jpg",
        "description": "還有這樣太不負責了吧"
    },
    {
        "name": "不要",
        "file_name": "不要.jpg",
        "description": "出自第8集，祥子嚴厲拒絕並警告爽世時，爽世的崩潰台詞",
        "tags": ["爽世", "祥子"],
        "author": "爽世",
        "episode": 8
    },
    {
        "name": "愛音愛心",
        "file_name": "愛音愛心.jpg",
        "description": "愛音愛心"
    },
    {
        "name": "爽世看手機",
        "file_name": "爽世看手機.jpg",
        "description": "爽世看手機"
    },
    {
        "name": "我已經徹底失敗了",
        "file_name": "我已經徹底失敗了.jpg",
        "description": "我已經徹底失敗了"
    },
    {
        "name": "她真的好溫柔喔",
        "file_name": "她真的好溫柔喔.jpg",
        "description": "她真的好溫柔喔"
    },
    {
        "name": "已經死了",
        "file_name": "已經死了.jpg",
        "description": "已經死了"
    },
    {
        "name": "有趣的女人",
        "file_name": "有趣的女人.jpg",
        "description": "有趣的女人"
    },
    {
        "name": "這是夢嗎",
        "file_name": "這是夢嗎.jpg",
        "description": "這是夢嗎"
    },
    {
        "name": "妳是抱著多大的覺悟說出這種話的",
        "file_name": "妳是抱著多大的覺悟說出這種話的.jpg",
        "description": "妳是抱著多大的覺悟說出這種話的"
    },
    {
        "name": "不是這樣",
        "file_name": "不是這樣.jpg",
        "description": "出自第9集，立希在練習室和大家坦白時，燈的反駁詞",
        "tags": ["燈", "第9集"],
        "author": "燈",
        "episode": 9
    },
    {
        "name": "爽世驚訝",
        "file_name": "爽世驚訝.jpg",
        "description": "爽世驚訝"
    },
    {
        "name": "怎麼了嗎",
        "file_name": "怎麼了嗎.jpg",
        "description": "怎麼了嗎"
    },
    {
        "name": "人生這麼漫長會撐不住的喔",
        "file_name": "人生這麼漫長會撐不住的喔.jpg",
        "description": "出自第1集，愛音在KTV敷衍燈時的鼓勵詞",
        "tags": ["愛音", "人生"],
        "author": "愛音",
        "episode": 1
    },
    {
        "name": "到現在還執著於過去，真難看",
        "file_name": "到現在還執著於過去，真難看.jpg",
        "description": "出自第8集，祥子和爽世的談判中祥子對爽世的攻擊",
        "tags": ["祥子"],
        "author": "祥子",
        "episode": 8
    },
    {
        "name": "是啊，到底為什麼呢",
        "file_name": "是啊，到底為什麼呢.jpg",
        "description": "是啊，到底為什麼呢"
    },
    {
        "name": "妳也為別人設想一下嘛",
        "file_name": "妳也為別人設想一下嘛.jpg",
        "description": "妳也為別人設想一下嘛"
    },
    {
        "name": "無趣的女孩子",
        "file_name": "無趣的女孩子.jpg",
        "description": "無趣的女孩子"
    },
    {
        "name": "真是遺憾",
        "file_name": "真是遺憾.jpg",
        "description": "真是遺憾"
    },
    {
        "name": "沒錯沒錯",
        "file_name": "沒錯沒錯.jpg",
        "description": "沒錯沒錯"
    },
    {
        "name": "妳很煩欸",
        "file_name": "妳很煩欸.jpg",
        "description": "妳很煩欸"
    },
    {
        "name": "真是太好了",
        "file_name": "真是太好了.jpg",
        "description": "真是太好了"
    },
    {
        "name": "一旦加入就無法回頭了喔",
        "file_name": "一旦加入就無法回頭了喔.jpg",
        "description": "出自第13集，睦表示要加入ave_mujica，祥子說出的對白",
        "tags": ["祥子", "睦"],
        "author": "祥子",
        "episode": 13
    },
    {
        "name": "怎麼這麼問",
        "file_name": "怎麼這麼問.jpg",
        "description": "怎麼這麼問"
    },
    {
        "name": "我哪裡有興奮了",
        "file_name": "我哪裡有興奮了.jpg",
        "description": "我哪裡有興奮了"
    },
    {
        "name": "可以請妳別提起那件事嗎",
        "file_name": "可以請妳別提起那件事嗎.jpg",
        "description": "出自第8集，初華踩雷時祥子的防禦",
        "tags": ["祥子", "初華"],
        "author": "祥子",
        "episode": 8
    },
    {
        "name": "妳不是不需要我了嗎",
        "file_name": "妳不是不需要我了嗎.jpg",
        "description": "妳不是不需要我了嗎"
    },
    {
        "name": "我不論如何都想當面向妳道歉",
        "file_name": "我不論如何都想當面向妳道歉.jpg",
        "description": "我不論如何都想當面向妳道歉"
    },
    {
        "name": "就是這個",
        "file_name": "就是這個.jpg",
        "description": "就是這個"
    },
    {
        "name": "我現在要講很感性的話，聽我說嘛",
        "file_name": "我現在要講很感性的話，聽我說嘛.jpg",
        "description": "我現在要講很感性的話，聽我說嘛"
    },
    {
        "name": "祝妳幸福",
        "file_name": "祝妳幸福.jpg",
        "description": "祝妳幸福"
    },
    {
        "name": "太棒了，爽世同學LOVE",
        "file_name": "太棒了，爽世同學LOVE.jpg",
        "description": "出自第2集，愛音對於爽世答應組樂團的喜悅反應",
        "tags": ["愛音"],
        "author": "愛音",
        "episode": 2
    },
    {
        "name": "大家真沒品味",
        "file_name": "大家真沒品味.jpg",
        "description": "出自第11集，愛音出的主意被眾人駁回後的反應",
        "tags": ["愛音"],
        "author": "愛音",
        "episode": 11
    },
    {
        "name": "真是會虛情假意呢",
        "file_name": "真是會虛情假意呢.jpg",
        "description": "真是會虛情假意呢"
    },
    {
        "name": "可以請妳刪除剛才的影片嗎",
        "file_name": "可以請妳刪除剛才的影片嗎.jpg",
        "description": "出自第13集，喵夢跑去偷拍舞台被抓包，祥子要求刪除影片",
        "tags": ["祥子","喵夢","若麥"],
        "author": "祥子",
        "episode": 13
    },
    {
        "name": "全是一些無趣的女人",
        "file_name": "全是一些無趣的女人.jpg",
        "description": "出自第5集，貓貓擅自跑進去練習室後，mygo成員們問話，貓貓的反應",
        "tags": ["樂奈", "貓貓"],
        "author": "樂奈",
        "episode": 5
    },
    {
        "name": "燈：我不知道",
        "file_name": "我不知道.jpg",
        "description": "我不知道"
    },
    {
        "name": "我還是會繼續下去",
        "file_name": "我還是會繼續下去.jpg",
        "description": "我還是會繼續下去"
    },
    {
        "name": "是妳先來找我麻煩的吧",
        "file_name": "是妳先來找我麻煩的吧.jpg",
        "description": "是妳先來找我麻煩的吧"
    },
    {
        "name": "妳這話是認真的嗎",
        "file_name": "妳這話是認真的嗎.jpg",
        "description": "出自第9集，立希到爽世學校堵人質疑爽世的話",
        "tags": ["爽世", "立希"],
        "author": "立希",
        "episode": 9
    },
    {
        "name": "不要這樣",
        "file_name": "不要這樣.jpg",
        "description": "出自第13集，ave_mujica初次公演時的台詞",
        "tags": ["mujica", "祥子"],
        "author": "祥子",
        "episode": 13
    },
    {
        "name": "態度好差喔",
        "file_name": "態度好差喔.jpg",
        "description": "態度好差喔"
    },
    {
        "name": "有點不太能想像呢",
        "file_name": "有點不太能想像呢.jpg",
        "description": "有點不太能想像呢"
    },
    {
        "name": "掰掰",
        "file_name": "掰掰.jpg",
        "description": "掰掰"
    },
    {
        "name": "我哪有可能有辦法",
        "file_name": "我哪有可能有辦法.jpg",
        "description": "我哪有可能有辦法"
    },
    {
        "name": "我需要愛音",
        "file_name": "我需要愛音.jpg",
        "description": "我需要愛音"
    },
    {
        "name": "妳到底想幹嘛",
        "file_name": "妳到底想幹嘛.jpg",
        "description": "妳到底想幹嘛"
    },
    {
        "name": "那些不是重點吧",
        "file_name": "那些不是重點吧.jpg",
        "description": "那些不是重點吧"
    },
    {
        "name": "從來不覺得玩樂團開心過",
        "file_name": "從來不覺得玩樂團開心過.jpg",
        "description": "從來不覺得玩樂團開心過"
    },
    {
        "name": "睦（笑）",
        "file_name": "睦_笑.jpg",
        "description": "睦（笑）"
    },
    {
        "name": "運氣真好",
        "file_name": "運氣真好.jpg",
        "description": "運氣真好"
    },
    {
        "name": "我害怕受到傷害",
        "file_name": "我害怕受到傷害.jpg",
        "description": "我害怕受到傷害"
    },
    {
        "name": "這種事不重要吧",
        "file_name": "這種事不重要吧.jpg",
        "description": "出自第10集，愛音在天台上被燈追問加入樂團的理由時說的話",
        "tags": ["愛音", "愛慕虛榮"],
        "author": "愛音",
        "episode": 10
    },
    {
        "name": "妳有好好看訊息嗎",
        "file_name": "妳有好好看訊息嗎.jpg",
        "description": "出自第8集，凜凜子對都不看訊息的樂奈說的台詞",
        "tags": ["凜凜子", "樂奈", "看訊息"],
        "author": "凜凜子",
        "episode": 8
    },
    {
        "name": "是啊",
        "file_name": "是啊.jpg",
        "description": "出自第9集，爽世和立希直球談判時說的Sodayo",
        "tags": ["立希", "爽世"],
        "author": "爽世",
        "episode": 9
    },
    {
        "name": "那當然是騙人的啊",
        "file_name": "那當然是騙人的啊.jpg",
        "description": "出自第9集，爽世表示一開始的誓言都是為了重建Crichic的謊言",
        "tags": ["立希", "爽世", "騙人"],
        "author": "爽世",
        "episode": 9
    },
    {
        "name": "還真是高高在上呢",
        "file_name": "還真是高高在上呢.jpg",
        "description": "出自第13集，睦表示覺得祥子快壞掉了，祥子對睦說的台詞",
        "tags": ["祥子", "睦"],
        "author": "祥子",
        "episode": 13
    },
    {
        "name": "不要吼我啦",
        "file_name": "不要吼我啦.jpg",
        "description": "出自第6集，立希兇愛音被爆發的愛音回嘴",
        "tags": ["立希", "愛音"],
        "author": "愛音",
        "episode": 6
    },
    {
        "name": "是嗎",
        "file_name": "是嗎2.jpg",
        "description": "出自第11集，爽世說的是嗎",
        "tags": ["爽世"],
        "author": "爽世",
        "episode": 11
    },
    {
        "name": "不知道",
        "file_name": "爽世_不知道.jpg",
        "description": "出自第9集，爽世與立希直球對決，對要不要樂團的處置表示不知道",
        "tags": ["立希", "爽世"],
        "author": "爽世",
        "episode": 9
    },
    {
        "name": "初華看手機",
        "file_name": "初華看手機.jpg",
        "description": "出自第4集，片尾初華和真奈講完話之後拿出手機",
        "tags": ["初華"],
        "author": "初華",
        "episode": 4
    },
    {
        "name": "祥子看手機",
        "file_name": "祥子看手機.jpg",
        "description": "出自第3集，在Crichic初次live後祥子收到噩耗時的表情",
        "tags": ["祥子"],
        "author": "祥子",
        "episode": 3
    },
    {
        "name": "騙人是什麼意思",
        "file_name": "騙人是什麼意思.jpg",
        "description": "出自第9集，立希講出爽世是在騙人時眾人的反應",
        "tags": ["愛音", "立希"],
        "author": "愛音",
        "episode": 9
    },
    {
        "name": "需要我待會再過來嗎",
        "file_name": "需要我待會再過來嗎.jpg",
        "description": "出自第9集，海鈴見到mygo成員正在爭吵時說出的話",
        "tags": ["海鈴"],
        "author": "海鈴",
        "episode": 9
    },
    {
        "name": "那傢伙已經不行了",
        "file_name": "那傢伙已經不行了.jpg",
        "description": "出自第9集，立希和團員說有找海鈴時說爽世不會不行了",
        "tags": ["立希"],
        "author": "立希",
        "episode": 9
    },
    {
        "name": "那傢伙不會回來了",
        "file_name": "那傢伙不會回來了.jpg",
        "description": "出自第9集，立希講出爽世是在騙人之後說的話",
        "tags": ["立希"],
        "author": "立希",
        "episode": 9
    },
    {
        "name": "妳怎麼不找我們去",
        "file_name": "妳怎麼不找我們去.jpg",
        "description": "",
        "tags": [],
        "author": "",
        "episode": 0
    },
    {
        "name": "妳這話是認真的嗎",
        "file_name": "妳這話是認真的嗎.jpg",
        "description": "",
        "tags": [],
        "author": "",
        "episode": 0
    },
    {
        "name": "為什麼",
        "file_name": "為什麼.jpg",
        "description": "",
        "tags": [],
        "author": "",
        "episode": 0
    },
    {
        "name": "相信也不會有人責怪我的",
        "file_name": "相信也不會有人責怪我的.jpg",
        "description": "",
        "tags": [],
        "author": "",
        "episode": 0
    },
    {
        "name": "痛痛啊痛痛啊快飛走吧",
        "file_name": "痛痛啊痛痛啊快飛走吧.jpg",
        "description": "",
        "tags": [],
        "author": "",
        "episode": 0
    },
    {
        "name": "做事笨拙總是徒勞",
        "file_name": "做事笨拙總是徒勞.jpg",
        "description": "",
        "tags": [],
        "author": "",
        "episode": 0
    },
    {
        "name": "差勁2",
        "file_name": "差勁2.jpg",
        "description": "",
        "tags": [],
        "author": "",
        "episode": 0
    },
    {
        "name": "這麼快等一下啦",
        "file_name": "這麼快等一下啦.jpg",
        "description": "",
        "tags": [],
        "author": "",
        "episode": 0
    },
    {
        "name": "妳對組樂團有興趣嗎",
        "file_name": "妳對組樂團有興趣嗎.jpg",
        "description": "",
        "tags": [],
        "author": "",
        "episode": 0
    },
    {
        "name": "貴安",
        "file_name": "貴安.jpg",
        "description": "",
        "tags": [],
        "author": "",
        "episode": 0
    },
    {
        "name": "真是讓人活得難受的世界啊",
        "file_name": "真是讓人活得難受的世界啊.jpg",
        "description": "",
        "tags": [],
        "author": "",
        "episode": 0
    },
    {
        "name": "要做什麼",
        "file_name": "要做什麼.jpg",
        "description": "",
        "tags": [],
        "author": "",
        "episode": 0
    },
    {
        "name": "感覺不錯",
        "file_name": "感覺不錯.jpg",
        "description": "",
        "tags": [],
        "author": "",
        "episode": 0
    },
    {
        "name": "真的嗎太好了",
        "file_name": "真的嗎太好了.jpg",
        "description": "",
        "tags": [],
        "author": "",
        "episode": 0
    },
    {
        "name": "但可能只是我們會錯意啊",
        "file_name": "但可能只是我們會錯意啊.jpg",
        "description": "",
        "tags": [],
        "author": "",
        "episode": 0
    },
    {
        "name": "那我也要",
        "file_name": "那我也要.jpg",
        "description": "",
        "tags": [],
        "author": "",
        "episode": 0
    },
    {
        "name": "我有安排了",
        "file_name": "我有安排了.jpg",
        "description": "",
        "tags": [],
        "author": "",
        "episode": 0
    },
    {
        "name": "只要有小燈在就夠了吧",
        "file_name": "只要有小燈在就夠了吧.jpg",
        "description": "",
        "tags": [],
        "author": "",
        "episode": 0
    },
    {
        "name": "冒昧請教妳一件事",
        "file_name": "冒昧請教妳一件事.jpg",
        "description": "",
        "tags": [],
        "author": "",
        "episode": 0
    },
    {
        "name": "那些全都是騙人的",
        "file_name": "那些全都是騙人的.jpg",
        "description": "",
        "tags": [],
        "author": "",
        "episode": 0
    },
    {
        "name": "過來吧",
        "file_name": "過來吧.jpg",
        "description": "",
        "tags": [],
        "author": "",
        "episode": 0
    },
    {
        "name": "是這個意思嗎",
        "file_name": "是這個意思嗎.jpg",
        "description": "",
        "tags": [],
        "author": "",
        "episode": 0
    },
    {
        "name": "我受夠了所以我才",
        "file_name": "我受夠了所以我才.jpg",
        "description": "",
        "tags": [],
        "author": "",
        "episode": 0
    },
    {
        "name": "這裡就是我們的新家喔",
        "file_name": "這裡就是我們的新家喔.jpg",
        "description": "",
        "tags": [],
        "author": "",
        "episode": 0
    },
    {
        "name": "已經和我沒有關係了",
        "file_name": "已經和我沒有關係了.jpg",
        "description": "",
        "tags": [],
        "author": "",
        "episode": 0
    },
    {
        "name": "讓妳們久等了",
        "file_name": "讓妳們久等了.jpg",
        "description": "",
        "tags": [],
        "author": "",
        "episode": 0
    },
    {
        "name": "已經不可能了",
        "file_name": "已經不可能了.jpg",
        "description": "",
        "tags": [],
        "author": "",
        "episode": 0
    },
    {
        "name": "我們沒辦法再重新開始嗎",
        "file_name": "我們沒辦法再重新開始嗎.jpg",
        "description": "",
        "tags": [],
        "author": "",
        "episode": 0
    },
    {
        "name": "妳在做甚麼",
        "file_name": "妳在做甚麼.jpg",
        "description": "",
        "tags": [],
        "author": "",
        "episode": 0
    },
    {
        "name": "媽媽很棒對不對",
        "file_name": "媽媽很棒對不對.jpg",
        "description": "",
        "tags": [],
        "author": "",
        "episode": 0
    },
    {
        "name": "就表示不需要這傢伙了吧",
        "file_name": "就表示不需要這傢伙了吧.jpg",
        "description": "",
        "tags": [],
        "author": "",
        "episode": 0
    },
    {
        "name": "等一下",
        "file_name": "等一下.jpg",
        "description": "",
        "tags": [],
        "author": "",
        "episode": 0
    },
    {
        "name": "那個誓言呢",
        "file_name": "那個誓言呢.jpg",
        "description": "",
        "tags": [],
        "author": "",
        "episode": 0
    },
    {
        "name": "樂團不需要我了吧",
        "file_name": "樂團不需要我了吧.jpg",
        "description": "",
        "tags": [],
        "author": "",
        "episode": 0
    },
    {
        "name": "等一下啦",
        "file_name": "等一下啦.jpg",
        "description": "",
        "tags": [],
        "author": "",
        "episode": 0
    },
    {
        "name": "畏畏縮縮哭哭啼啼的我",
        "file_name": "畏畏縮縮哭哭啼啼的我.jpg",
        "description": "",
        "tags": [],
        "author": "",
        "episode": 0
    },
    {
        "name": "就算稍稍喘口氣休息一下",
        "file_name": "就算稍稍喘口氣休息一下.jpg",
        "description": "",
        "tags": [],
        "author": "",
        "episode": 0
    },
    {
        "name": "再繼續四分五裂下去",
        "file_name": "再繼續四分五裂下去.jpg",
        "description": "",
        "tags": [],
        "author": "",
        "episode": 0
    },
    {
        "name": "到底是哪個",
        "file_name": "到底是哪個.jpg",
        "description": "",
        "tags": [],
        "author": "",
        "episode": 0
    },
    {
        "name": "不行了",
        "file_name": "不行了.jpg",
        "description": "",
        "tags": [],
        "author": "",
        "episode": 0
    },
    {
        "name": "我是因為要利用她才表現得很溫柔",
        "file_name": "我是因為要利用她才表現得很溫柔.jpg",
        "description": "",
        "tags": [],
        "author": "",
        "episode": 0
    },
    {
        "name": "妳今天有空嗎",
        "file_name": "妳今天有空嗎.jpg",
        "description": "",
        "tags": [],
        "author": "",
        "episode": 0
    },
    {
        "name": "我都會盡可能參加",
        "file_name": "我都會盡可能參加.jpg",
        "description": "",
        "tags": [],
        "author": "",
        "episode": 0
    },
    {
        "name": "我一直非常期待能和各位見面1",
        "file_name": "我一直非常期待能和各位見面1.jpg",
        "description": "",
        "tags": [],
        "author": "",
        "episode": 0
    },
    {
        "name": "請多多指教",
        "file_name": "請多多指教.jpg",
        "description": "",
        "tags": [],
        "author": "",
        "episode": 0
    },
    {
        "name": "我和那傢伙談過了",
        "file_name": "我和那傢伙談過了.jpg",
        "description": "",
        "tags": [],
        "author": "",
        "episode": 0
    },
    {
        "name": "這一切的一切全都是我",
        "file_name": "這一切的一切全都是我.jpg",
        "description": "",
        "tags": [],
        "author": "",
        "episode": 0
    },
    {
        "name": "什麼叫不是這樣",
        "file_name": "什麼叫不是這樣.jpg",
        "description": "",
        "tags": [],
        "author": "",
        "episode": 0
    },
    {
        "name": "走吧",
        "file_name": "走吧.jpg",
        "description": "",
        "tags": [],
        "author": "",
        "episode": 0
    },
    {
        "name": "妳要不要先去洗澡",
        "file_name": "妳要不要先去洗澡.jpg",
        "description": "",
        "tags": [],
        "author": "",
        "episode": 0
    },
    {
        "name": "我會繼續做自己的夥伴",
        "file_name": "我會繼續做自己的夥伴.jpg",
        "description": "",
        "tags": [],
        "author": "",
        "episode": 0
    },
    {
        "name": "可以和我一起過去看看嗎",
        "file_name": "可以和我一起過去看看嗎.jpg",
        "description": "",
        "tags": [],
        "author": "",
        "episode": 0
    },
    {
        "name": "不想組什麼樂團的",
        "file_name": "不想組什麼樂團的.jpg",
        "description": "",
        "tags": [],
        "author": "",
        "episode": 0
    },
    {
        "name": "沒有不可能",
        "file_name": "沒有不可能.jpg",
        "description": "",
        "tags": [],
        "author": "",
        "episode": 0
    },
    {
        "name": "誓言",
        "file_name": "誓言.jpg",
        "description": "",
        "tags": [],
        "author": "",
        "episode": 0
    },
    {
        "name": "那些妳全都知道卻一直在背叛她嗎",
        "file_name": "那些妳全都知道卻一直在背叛她嗎.jpg",
        "description": "",
        "tags": [],
        "author": "",
        "episode": 0
    },
    {
        "name": "原來如此",
        "file_name": "原來如此.jpg",
        "description": "",
        "tags": [],
        "author": "",
        "episode": 0
    },
    {
        "name": "真是稀奇呢",
        "file_name": "真是稀奇呢.jpg",
        "description": "",
        "tags": [],
        "author": "",
        "episode": 0
    },
    {
        "name": "所以妳要問什麼",
        "file_name": "所以妳要問什麼.jpg",
        "description": "",
        "tags": [],
        "author": "",
        "episode": 0
    },
    {
        "name": "我也很想去喔",
        "file_name": "我也很想去喔.jpg",
        "description": "",
        "tags": [],
        "author": "",
        "episode": 0
    },
    {
        "name": "這邊這邊",
        "file_name": "這邊這邊.jpg",
        "description": "",
        "tags": [],
        "author": "",
        "episode": 0
    },
    {
        "name": "要是沒有小祥妳們的話我就",
        "file_name": "要是沒有小祥妳們的話我就.jpg",
        "description": "",
        "tags": [],
        "author": "",
        "episode": 0
    },
    {
        "name": "要不要過去看看",
        "file_name": "要不要過去看看.jpg",
        "description": "",
        "tags": [],
        "author": "",
        "episode": 0
    },
    {
        "name": "只有我這麼想嗎",
        "file_name": "只有我這麼想嗎.jpg",
        "description": "",
        "tags": [],
        "author": "",
        "episode": 0
    },
    {
        "name": "有辦法背負其他人的人生嗎",
        "file_name": "有辦法背負其他人的人生嗎.jpg",
        "description": "",
        "tags": [],
        "author": "",
        "episode": 0
    },
    {
        "name": "我們一定傷害到妳了吧",
        "file_name": "我們一定傷害到妳了吧.jpg",
        "description": "",
        "tags": [],
        "author": "",
        "episode": 0
    },
    {
        "name": "因為我也有點在意",
        "file_name": "因為我也有點在意.jpg",
        "description": "",
        "tags": [],
        "author": "",
        "episode": 0
    },
    {
        "name": "甚麼都願意做就是這麼沉重的話",
        "file_name": "甚麼都願意做就是這麼沉重的話.jpg",
        "description": "",
        "tags": [],
        "author": "",
        "episode": 0
    },
    {
        "name": "我不論如何都想向妳道歉",
        "file_name": "我不論如何都想向妳道歉.jpg",
        "description": "",
        "tags": [],
        "author": "",
        "episode": 0
    },
    {
        "name": "我實在沒有辦法",
        "file_name": "我實在沒有辦法.jpg",
        "description": "",
        "tags": [],
        "author": "",
        "episode": 0
    },
    {
        "name": "做不來的事就別隨便說出口",
        "file_name": "做不來的事就別隨便說出口.jpg",
        "description": "",
        "tags": [],
        "author": "",
        "episode": 0
    },
    {
        "name": "今後不要再和我扯上關係了",
        "file_name": "今後不要再和我扯上關係了.jpg",
        "description": "",
        "tags": [],
        "author": "",
        "episode": 0
    },
    {
        "name": "這是最後的警告",
        "file_name": "這是最後的警告.jpg",
        "description": "",
        "tags": [],
        "author": "",
        "episode": 0
    },
    {
        "name": "沒有人那樣拜託妳",
        "file_name": "沒有人那樣拜託妳.jpg",
        "description": "",
        "tags": [],
        "author": "",
        "episode": 0
    },
    {
        "name": "求求妳",
        "file_name": "求求妳.jpg",
        "description": "",
        "tags": [],
        "author": "",
        "episode": 0
    },
    {
        "name": "謝謝妳今天願意來見我",
        "file_name": "謝謝妳今天願意來見我.jpg",
        "description": "",
        "tags": [],
        "author": "",
        "episode": 0
    },
    {
        "name": "我有哪裡有誤會了",
        "file_name": "我有哪裡有誤會了.jpg",
        "description": "",
        "tags": [],
        "author": "",
        "episode": 0
    },
    {
        "name": "妳為什麼要我忘記呢",
        "file_name": "妳為什麼要我忘記呢.jpg",
        "description": "",
        "tags": [],
        "author": "",
        "episode": 0
    },
    {
        "name": "妳是抱著多大的覺悟說出這種話的",
        "file_name": "妳是抱著多大的覺悟說出這種話的.jpg",
        "description": "",
        "tags": [],
        "author": "",
        "episode": 0
    },
    {
        "name": "放開我",
        "file_name": "祥子放開我.jpg",
        "description": "",
        "tags": [],
        "author": "",
        "episode": 0
    },
    {
        "name": "我們本來真的沒有要演奏春日影的",
        "file_name": "我們本來真的沒有要演奏春日影的.jpg",
        "description": "",
        "tags": [],
        "author": "",
        "episode": 0
    },
    {
        "name": "可是我真的",
        "file_name": "可是我真的.jpg",
        "description": "",
        "tags": [],
        "author": "",
        "episode": 0
    },
    {
        "name": "不要走",
        "file_name": "不要走.jpg",
        "description": "",
        "tags": [],
        "author": "",
        "episode": 0
    },
    {
        "name": "絕對不可能再復活了",
        "file_name": "絕對不可能再復活了.jpg",
        "description": "",
        "tags": [],
        "author": "",
        "episode": 0
    },
    {
        "name": "那又怎麼樣",
        "file_name": "那又怎麼樣.jpg",
        "description": "",
        "tags": [],
        "author": "",
        "episode": 0
    },
    {
        "name": "妳講的話和做的事全都互相矛盾",
        "file_name": "妳講的話和做的事全都互相矛盾.jpg",
        "description": "",
        "tags": [],
        "author": "",
        "episode": 0
    },
    {
        "name": "我們以前感情明明那麼好",
        "file_name": "我們以前感情明明那麼好.jpg",
        "description": "",
        "tags": [],
        "author": "",
        "episode": 0
    },
    {
        "name": "妳也差不多該忘記了吧",
        "file_name": "妳也差不多該忘記了吧.jpg",
        "description": "",
        "tags": [],
        "author": "",
        "episode": 0
    },
    {
        "name": "真的很對不起",
        "file_name": "真的很對不起.jpg",
        "description": "",
        "tags": [],
        "author": "",
        "episode": 0
    },
    {
        "name": "大家每天都快樂地相處在一起",
        "file_name": "大家每天都快樂地相處在一起.jpg",
        "description": "",
        "tags": [],
        "author": "",
        "episode": 0
    },
    {
        "name": "可是",
        "file_name": "可是.jpg",
        "description": "",
        "tags": [],
        "author": "",
        "episode": 0
    },
    {
        "name": "妳這個人",
        "file_name": "妳這個人.jpg",
        "description": "",
        "tags": [],
        "author": "",
        "episode": 0
    },
    {
        "name": "妳們就請便吧",
        "file_name": "妳們就請便吧.jpg",
        "description": "",
        "tags": [],
        "author": "",
        "episode": 0
    },
    {
        "name": "那些跟現在有關係嗎",
        "file_name": "那些跟現在有關係嗎.jpg",
        "description": "",
        "tags": [],
        "author": "",
        "episode": 0
    },
    {
        "name": "什麼跟什麼啊",
        "file_name": "什麼跟什麼啊.jpg",
        "description": "",
        "tags": [],
        "author": "",
        "episode": 0
    },
    {
        "name": "那個",
        "file_name": "那個.jpg",
        "description": "",
        "tags": [],
        "author": "",
        "episode": 0
    },
    {
        "name": "也不是這樣",
        "file_name": "也不是這樣.jpg",
        "description": "",
        "tags": [],
        "author": "",
        "episode": 0
    },
    {
        "name": "我在這裡再次感謝大家今天願意參加集會",
        "file_name": "我在這裡再次感謝大家今天願意參加集會.jpg",
        "description": "",
        "tags": [],
        "author": "",
        "episode": 0
    },
    {
        "name": "動機太不單純了",
        "file_name": "動機太不單純了.jpg",
        "description": "",
        "tags": [],
        "author": "",
        "episode": 0
    },
    {
        "name": "我沒聽過這首歌",
        "file_name": "我沒聽過這首歌.jpg",
        "description": "",
        "tags": [],
        "author": "",
        "episode": 0
    },
    {
        "name": "妳好",
        "file_name": "妳好.jpg",
        "description": "",
        "tags": [],
        "author": "",
        "episode": 0
    },
    {
        "name": "普通和理所當然到底是什麼呢",
        "file_name": "普通和理所當然到底是什麼呢.jpg",
        "description": "",
        "tags": [],
        "author": "",
        "episode": 0
    },
    {
        "name": "妳不記得了嗎",
        "file_name": "妳不記得了嗎.jpg",
        "description": "",
        "tags": [],
        "author": "",
        "episode": 0
    },
    {
        "name": "理想不會放得太高了嗎",
        "file_name": "理想不會放得太高了嗎.jpg",
        "description": "",
        "tags": [],
        "author": "",
        "episode": 0
    },
    {
        "name": "我也會努力看看的",
        "file_name": "我也會努力看看的.jpg",
        "description": "",
        "tags": [],
        "author": "",
        "episode": 0
    },
    {
        "name": "不是按那邊啦",
        "file_name": "不是按那邊啦.jpg",
        "description": "",
        "tags": [],
        "author": "",
        "episode": 0
    },
    {
        "name": "等一下再來聽聽看吧",
        "file_name": "等一下再來聽聽看吧.jpg",
        "description": "",
        "tags": [],
        "author": "",
        "episode": 0
    },
    {
        "name": "這問題問得好",
        "file_name": "這問題問得好.jpg",
        "description": "",
        "tags": [],
        "author": "",
        "episode": 0
    },
    {
        "name": "我家裡有",
        "file_name": "我家裡有.jpg",
        "description": "",
        "tags": [],
        "author": "",
        "episode": 0
    },
    {
        "name": "她和我約好要一輩子組樂團了",
        "file_name": "她和我約好要一輩子組樂團了.jpg",
        "description": "",
        "tags": [],
        "author": "",
        "episode": 0
    },
    {
        "name": "妳在幹嘛啊",
        "file_name": "妳在幹嘛啊.jpg",
        "description": "",
        "tags": [],
        "author": "",
        "episode": 0
    },
    {
        "name": "Soyorin",
        "file_name": "Soyorin.jpg",
        "description": "",
        "tags": [],
        "author": "",
        "episode": 0
    },
    {
        "name": "不是不是",
        "file_name": "不是不是.jpg",
        "description": "",
        "tags": [],
        "author": "",
        "episode": 0
    },
    {
        "name": "她笑了",
        "file_name": "她笑了.jpg",
        "description": "",
        "tags": [],
        "author": "",
        "episode": 0
    },
    {
        "name": "光是會寫就很厲害了",
        "file_name": "光是會寫就很厲害了.jpg",
        "description": "",
        "tags": [],
        "author": "",
        "episode": 0
    },
    {
        "name": "我",
        "file_name": "我.jpg",
        "description": "",
        "tags": [],
        "author": "",
        "episode": 0
    },
    {
        "name": "不可能吧",
        "file_name": "不可能吧.jpg",
        "description": "",
        "tags": [],
        "author": "",
        "episode": 0
    },
    {
        "name": "可以請妳做個自我介紹嗎",
        "file_name": "可以請妳做個自我介紹嗎.jpg",
        "description": "",
        "tags": [],
        "author": "",
        "episode": 0
    },
    {
        "name": "我就是有認真想才提這個的啊",
        "file_name": "我就是有認真想才提這個的啊.jpg",
        "description": "",
        "tags": [],
        "author": "",
        "episode": 0
    },
    {
        "name": "一起共同演奏音樂的命運共同體了",
        "file_name": "一起共同演奏音樂的命運共同體了.jpg",
        "description": "",
        "tags": [],
        "author": "",
        "episode": 0
    },
    {
        "name": "有人回覆嗎",
        "file_name": "有人回覆嗎.jpg",
        "description": "",
        "tags": [],
        "author": "",
        "episode": 0
    },
    {
        "name": "妳說什麼？",
        "file_name": "妳說什麼.jpg",
        "description": "",
        "tags": [],
        "author": "",
        "episode": 0
    },
    {
        "name": "他沒有說要退出",
        "file_name": "他沒有說要退出.jpg",
        "description": "",
        "tags": [],
        "author": "",
        "episode": 0
    },
    {
        "name": "對不起",
        "file_name": "對不起.jpg",
        "description": "",
        "tags": [],
        "author": "",
        "episode": 0
    },
    {
        "name": "唱得很棒喔",
        "file_name": "唱得很棒喔.jpg",
        "description": "",
        "tags": [],
        "author": "",
        "episode": 0
    },
    {
        "name": "請慢慢享用",
        "file_name": "請慢慢享用.jpg",
        "description": "",
        "tags": [],
        "author": "",
        "episode": 0
    },
    {
        "name": "好厲害喔",
        "file_name": "好厲害喔.jpg",
        "description": "",
        "tags": [],
        "author": "",
        "episode": 0
    },
    {
        "name": "畢竟我們不過是群一丘之貂罷了",
        "file_name": "畢竟我們不過是群一丘之貂罷了.jpg",
        "description": "",
        "tags": [],
        "author": "",
        "episode": 0
    },
    {
        "name": "我就不用了",
        "file_name": "我就不用了.jpg",
        "description": "",
        "tags": [],
        "author": "",
        "episode": 0
    },
    {
        "name": "是沒關係沒錯",
        "file_name": "是沒關係沒錯.jpg",
        "description": "",
        "tags": [],
        "author": "",
        "episode": 0
    },
    {
        "name": "她也會緊張吧",
        "file_name": "她也會緊張吧.jpg",
        "description": "",
        "tags": [],
        "author": "",
        "episode": 0
    },
    {
        "name": "真讓人期待",
        "file_name": "真讓人期待.jpg",
        "description": "出自第3集，祥子表示要給眾人聽demo的鋼琴曲，此時的畫面帶到祥子，但說話的是爽世",
        "tags": ["祥子", "爽世"],
        "author": "爽世",
        "episode": 3
    },
    {
        "name": "麻煩妳了",
        "file_name": "麻煩妳了.jpg",
        "description": "",
        "tags": [],
        "author": "",
        "episode": 0
    },
    {
        "name": "以前時有耳聞",
        "file_name": "以前時有耳聞.jpg",
        "description": "",
        "tags": [],
        "author": "",
        "episode": 0
    },
    {
        "name": "好可以了",
        "file_name": "好可以了.jpg",
        "description": "",
        "tags": [],
        "author": "",
        "episode": 0
    },
    {
        "name": "一起加油吧",
        "file_name": "一起加油吧.jpg",
        "description": "",
        "tags": [],
        "author": "",
        "episode": 0
    },
    {
        "name": "妳叫什麼名字",
        "file_name": "妳叫什麼名字.jpg",
        "description": "",
        "tags": [],
        "author": "",
        "episode": 0
    },
    {
        "name": "這首是我的",
        "file_name": "這首是我的.jpg",
        "description": "",
        "tags": [],
        "author": "",
        "episode": 0
    },
    {
        "name": "不知道",
        "file_name": "不知道.jpg",
        "description": "",
        "tags": [],
        "author": "",
        "episode": 0
    },
    {
        "name": "讓人說不出話來了",
        "file_name": "讓人說不出話來了.jpg",
        "description": "",
        "tags": [],
        "author": "",
        "episode": 0
    },
    {
        "name": "請妳不要生小睦的氣喔",
        "file_name": "請妳不要生小睦的氣喔.jpg",
        "description": "",
        "tags": [],
        "author": "",
        "episode": 0
    },
    {
        "name": "全都失敗了",
        "file_name": "全都失敗了.jpg",
        "description": "",
        "tags": [],
        "author": "",
        "episode": 0
    },
    {
        "name": "那首歌真的很棒呢",
        "file_name": "那首歌真的很棒呢.jpg",
        "description": "",
        "tags": [],
        "author": "",
        "episode": 0
    },
    {
        "name": "可以吃了嗎",
        "file_name": "可以吃了嗎.jpg",
        "description": "",
        "tags": [],
        "author": "",
        "episode": 0
    },
    {
        "name": "太棒了",
        "file_name": "太棒了.jpg",
        "description": "",
        "tags": [],
        "author": "",
        "episode": 0
    },
    {
        "name": "不是啊",
        "file_name": "不是啊.jpg",
        "description": "",
        "tags": [],
        "author": "",
        "episode": 0
    },
    {
        "name": "現在的我們像是一盤散沙",
        "file_name": "現在的我們像是一盤散沙.jpg",
        "description": "",
        "tags": [],
        "author": "",
        "episode": 0
    },
    {
        "name": "看完了",
        "file_name": "看完了.jpg",
        "description": "",
        "tags": [],
        "author": "",
        "episode": 0
    },
    {
        "name": "我一直非常期待能和各位見面",
        "file_name": "我一直非常期待能和各位見面.jpg",
        "description": "",
        "tags": [],
        "author": "",
        "episode": 0
    },
    {
        "name": "我也好想看看喔",
        "file_name": "我也好想看看喔.jpg",
        "description": "",
        "tags": [],
        "author": "",
        "episode": 0
    },
    {
        "name": "我要封鎖他",
        "file_name": "我要封鎖他.jpg",
        "description": "",
        "tags": [],
        "author": "",
        "episode": 0
    },
    {
        "name": "不會有問題的",
        "file_name": "不會有問題的.jpg",
        "description": "",
        "tags": [],
        "author": "",
        "episode": 0
    },
    {
        "name": "想喝什麼都可以自己拿",
        "file_name": "想喝甚麼都可以自己拿.jpg",
        "description": "",
        "tags": [],
        "author": "",
        "episode": 0
    },
    {
        "name": "不會吧",
        "file_name": "不會吧.jpg",
        "description": "",
        "tags": [],
        "author": "",
        "episode": 0
    },
    {
        "name": "讓我深深受到感動",
        "file_name": "讓我深深受到感動.jpg",
        "description": "",
        "tags": [],
        "author": "",
        "episode": 0
    },
    {
        "name": "畢竟這是一輩子的事",
        "file_name": "畢竟這是一輩子的事.jpg",
        "description": "",
        "tags": [],
        "author": "",
        "episode": 0
    },
    {
        "name": "沒在開玩笑我是認真的",
        "file_name": "沒在開玩笑我是認真的.jpg",
        "description": "",
        "tags": [],
        "author": "",
        "episode": 0
    },
    {
        "name": "這布局可說是堅若磐石",
        "file_name": "這布局可說是堅若磐石.jpg",
        "description": "",
        "tags": [],
        "author": "",
        "episode": 0
    },
    {
        "name": "我會為妳加油的",
        "file_name": "我會為妳加油的.jpg",
        "description": "",
        "tags": [],
        "author": "",
        "episode": 0
    },
    {
        "name": "好好說明清楚",
        "file_name": "好好說明清楚.jpg",
        "description": "",
        "tags": [],
        "author": "",
        "episode": 0
    },
    {
        "name": "是這樣嗎",
        "file_name": "燈是這樣嗎.jpg",
        "description": "",
        "tags": [],
        "author": "",
        "episode": 0
    },
    {
        "name": "我們是MyGO",
        "file_name": "我們是MyGO.jpg",
        "description": "",
        "tags": [],
        "author": "",
        "episode": 0
    },
    {
        "name": "已經算跨出一大步了喔",
        "file_name": "已經算是跨出一大步了喔.jpg",
        "description": "",
        "tags": [],
        "author": "",
        "episode": 0
    },
    {
        "name": "爽世：太好了",
        "file_name": "太好了.jpg",
        "description": "",
        "tags": [],
        "author": "",
        "episode": 0
    },
    {
        "name": "就說我不用了啦",
        "file_name": "就說我不用了啦.jpg",
        "description": "",
        "tags": [],
        "author": "",
        "episode": 0
    },
    {
        "name": "It's my go耶, it's my go",
        "file_name": "Its_my_go耶,_its_my_go.jpg",
        "description": "",
        "tags": [],
        "author": "",
        "episode": 0
    },
    {
        "name": "祥子是這樣嗎",
        "file_name": "祥子是這樣嗎.jpg",
        "description": "",
        "tags": [],
        "author": "",
        "episode": 0
    },
    {
        "name": "那是歌詞嗎",
        "file_name": "那是歌詞嗎.jpg",
        "description": "",
        "tags": [],
        "author": "",
        "episode": 0
    },
    {
        "name": "我先去一下洗手間",
        "file_name": "我先去一下洗手間.jpg",
        "description": "",
        "tags": [],
        "author": "",
        "episode": 0
    },
    {
        "name": "祝妳幸福",
        "file_name": "祝妳幸福.jpg",
        "description": "",
        "tags": [],
        "author": "",
        "episode": 0
    },
    {
        "name": "我都還沒好好告訴過妳",
        "file_name": "我都還沒好好告訴過妳.jpg",
        "description": "",
        "tags": [],
        "author": "",
        "episode": 0
    },
    {
        "name": "要演奏什麼音樂",
        "file_name": "要演奏什麼音樂.jpg",
        "description": "",
        "tags": [],
        "author": "",
        "episode": 0
    },
    {
        "name": "那個誓言是騙人的",
        "file_name": "那個誓言是騙人的.jpg",
        "description": "",
        "tags": [],
        "author": "",
        "episode": 0
    },
    {
        "name": "妳唱得簡直太棒了",
        "file_name": "妳唱得簡直太棒了.jpg",
        "description": "",
        "tags": [],
        "author": "",
        "episode": 0
    },
    {
        "name": "我可以用嗎",
        "file_name": "我可以用嗎.jpg",
        "description": "",
        "tags": [],
        "author": "",
        "episode": 0
    },
    {
        "name": "是這種感覺啊",
        "file_name": "是這種感覺啊.jpg",
        "description": "",
        "tags": [],
        "author": "",
        "episode": 0
    },
    {
        "name": "真不愧是人氣寵兒",
        "file_name": "真不愧是人氣寵兒.jpg",
        "description": "",
        "tags": [],
        "author": "",
        "episode": 0
    },
    {
        "name": "真恐怖",
        "file_name": "真恐怖.jpg",
        "description": "",
        "tags": [],
        "author": "",
        "episode": 0
    },
    {
        "name": "現在正是復權的時刻",
        "file_name": "現在正是復權的時刻.jpg",
        "description": "",
        "tags": [],
        "author": "",
        "episode": 0
    },
    {
        "name": "這樣太奇怪了吧",
        "file_name": "這樣太奇怪了吧.jpg",
        "description": "",
        "tags": [],
        "author": "",
        "episode": 0
    },
    {
        "name": "我好想成為人類啊",
        "file_name": "我好想成為人類啊.jpg",
        "description": "",
        "tags": [],
        "author": "",
        "episode": 0
    },
    {
        "name": "人類真是殘酷",
        "file_name": "人類真是殘酷.jpg",
        "description": "",
        "tags": [],
        "author": "",
        "episode": 0
    },
    {
        "name": "我們一起叫吧",
        "file_name": "我們一起叫吧.jpg",
        "description": "",
        "tags": [],
        "author": "",
        "episode": 0
    },
    {
        "name": "這些該不會都是歌詞吧",
        "file_name": "這些該不會都是歌詞吧.jpg",
        "description": "",
        "tags": [],
        "author": "",
        "episode": 0
    },
    {
        "name": "妳只不過是一個學生",
        "file_name": "妳只不過是一個學生.jpg",
        "description": "",
        "tags": [],
        "author": "",
        "episode": 0
    },
    {
        "name": "盯...",
        "file_name": "盯....jpg",
        "description": "",
        "tags": [],
        "author": "",
        "episode": 0
    },
    {
        "name": "我看看",
        "file_name": "我看看.jpg",
        "description": "",
        "tags": [],
        "author": "",
        "episode": 0
    },
    {
        "name": "好溫柔",
        "file_name": "好溫柔.jpg",
        "description": "",
        "tags": [],
        "author": "",
        "episode": 0
    },
    {
        "name": "或許也不是真的不可能吧",
        "file_name": "或許也不是真的不可能吧.jpg",
        "description": "",
        "tags": [],
        "author": "",
        "episode": 0
    },
    {
        "name": "我都說一直都有在看了啊",
        "file_name": "我都說一直都有在看了啊.jpg",
        "description": "",
        "tags": [],
        "author": "",
        "episode": 0
    },
    {
        "name": "一丘之貂",
        "file_name": "一丘之貂.jpg",
        "description": "",
        "tags": [],
        "author": "",
        "episode": 0
    },
    {
        "name": "我們大家都很受傷",
        "file_name": "我們大家都很受傷.jpg",
        "description": "",
        "tags": [],
        "author": "",
        "episode": 0
    },
    {
        "name": "不是這樣的2",
        "file_name": "不是這樣的2.jpg",
        "description": "",
        "tags": [],
        "author": "",
        "episode": 0
    },
    {
        "name": "是啊(開心版)",
        "file_name": "是啊2.jpg",
        "description": "",
        "tags": [],
        "author": "",
        "episode": 0
    },
    {
        "name": "等一下妳是認真的嗎",
        "file_name": "等一下妳是認真的嗎.jpg",
        "description": "",
        "tags": [],
        "author": "",
        "episode": 0
    },
    {
        "name": "難道妳是第一次來嗎",
        "file_name": "難道妳是第一次來嗎.jpg",
        "description": "",
        "tags": [],
        "author": "",
        "episode": 0
    },
    {
        "name": "能不能也教我用呢",
        "file_name": "能不能也教我用呢.jpg",
        "description": "",
        "tags": [],
        "author": "",
        "episode": 0
    },
    {
        "name": "那傢伙根本就不打算組新樂團",
        "file_name": "那傢伙根本就不打算組新樂團.jpg",
        "description": "",
        "tags": [],
        "author": "",
        "episode": 0
    },
    {
        "name": "初華：太好了",
        "file_name": "太好了3.jpg",
        "description": "",
        "tags": [],
        "author": "",
        "episode": 0
    },
    {
        "name": "貓貓喝水",
        "file_name": "貓貓喝水.jpg",
        "description": "",
        "tags": [],
        "author": "",
        "episode": 0
    }
]